routerling/__init__.py
routerling/constants.py
routerling/context.py
routerling/errors.py
routerling/form.py
routerling/mocks.py
routerling/request.py
routerling/response.py
routerling/router.py
routerling/server.py
routerling/utils.py
routerling-0.5.1.dist-info/LICENSE
routerling-0.5.1.dist-info/WHEEL
routerling-0.5.1.dist-info/METADATA
routerling-0.5.1.dist-info/RECORD
