Metadata-Version: 2.1
Name: routerling
Version: 0.5.1
Summary: Extremely Stupid Simple, Blazing Fast, Get Out of your way immediately Microframework for building Python Web Applications.
License: MIT
Author: Raymond Ortserga
Author-email: ortserga@gmail.com
Requires-Python: >=3.6,<4.0
Classifier: License :: OSI Approved :: MIT License
Classifier: Programming Language :: Python :: 3
Classifier: Programming Language :: Python :: 3.6
Classifier: Programming Language :: Python :: 3.7
Classifier: Programming Language :: Python :: 3.8
Classifier: Programming Language :: Python :: 3.9
Classifier: Programming Language :: Python :: 3.10
Requires-Dist: uvicorn (>=0.14.0,<0.15.0)
